uscr/__init__.py
uscr/_modidx.py
uscr/_tmp.py
uscr/core.py
uscr-0.0.2.dist-info/LICENSE
uscr-0.0.2.dist-info/METADATA
uscr-0.0.2.dist-info/WHEEL
uscr-0.0.2.dist-info/entry_points.txt
uscr-0.0.2.dist-info/top_level.txt
uscr-0.0.2.dist-info/RECORD
