Metadata-Version: 2.1
Name: uscr
Version: 0.0.2
Summary: uscr (underscore string and string template class)
Home-page: https://github.com/dsm-72/uscr
Author: dsm-72
Author-email: sumner.magruder@yale.edu
License: Apache Software License 2.0
Keywords: uscr underscore dunder sunder mangled private string template class
Classifier: Development Status :: 4 - Beta
Classifier: Intended Audience :: Developers
Classifier: Natural Language :: English
Classifier: Programming Language :: Python :: 3.11
Classifier: License :: OSI Approved :: Apache Software License
Requires-Python: >=3.11
License-File: LICENSE
Requires-Dist: nchr
Requires-Dist: nlit
Provides-Extra: dev
